__init__.py
statementskeleton/__init__.py
statementskeleton/elements/Account.py
statementskeleton/elements/Divider.py
statementskeleton/elements/Element.py
statementskeleton/elements/Header.py
statementskeleton/elements/Spacer.py
statementskeleton/elements/Subtotal.py
statementskeleton/elements/Title.py
statementskeleton/elements/Total.py
statementskeleton/elements/__init__.py
statementskeleton/skeletons/Skeleton.py
statementskeleton/skeletons/__init__.py
statementskeleton-1.3.dist-info/LICENSE
statementskeleton-1.3.dist-info/METADATA
statementskeleton-1.3.dist-info/WHEEL
statementskeleton-1.3.dist-info/top_level.txt
statementskeleton-1.3.dist-info/RECORD
