Metadata-Version: 2.1
Name: statementskeleton
Version: 1.3
Summary: A package for formatting financial statements in the console. Designed for PyActy.
Author-email: Jacob Zufall <jacobzufall@gmail.com>
Project-URL: Homepage, https://github.com/JacobZufall/statementskeleton
Project-URL: Issues, https://github.com/JacobZufall/statementskeleton/issues
Classifier: Programming Language :: Python :: 3
Classifier: License :: OSI Approved :: GNU General Public License v2 (GPLv2)
Classifier: Operating System :: OS Independent
Requires-Python: >3.11
License-File: LICENSE
